<?xml version="1.0" encoding="utf-8"?>
<IncrementalBankBuild Version="6" Flags="878078161">
	<Platform GUID="{04BBD19B-288F-4B4E-B7AB-76336408720E}">
		<Banks>
			<Language ID="0">
				<File Name="Init" Hash="721438129" Timestamp="131289549014885880"/>
				<File Name="Main" Hash="4028747924" Timestamp="131289549920614620"/>
			</Language>
		</Banks>
		<XMLInfo>
			<Language ID="-1">
				<File Name="" Hash="4148626764" Timestamp="131289549920713756"/>
			</Language>
		</XMLInfo>
	</Platform>
</IncrementalBankBuild>
